{
    "puzzle": "BLUE_VITRIOL",
    "score": {
        "cost": 460,
        "instructions": 60,
        "overlap": false,
        "trackless": true,
        "cycles": 31,
        "area": 188,
        "height": 17,
        "width": 15.5,
        "rate": 4.0,
        "areaINF": {
            "level": 0,
            "value": 188.0
        },
        "heightINF": "17",
        "widthINF": 15.5
    },
    "displayLink": "https://files.mors.technology/BLUE_VITRIOL/460g-31c-188a-60i-T-71e599fa.mp4",
    "dataLink": "https://zlbb.faendir.com/l/om/7cf93b18/w3210151153/460g-60i-31c-188a-17h-15.5w-4r-188a0-17h-15.5w-T",
    "dataPath": "TOURNAMENT_2024/BLUE_VITRIOL/460g-60i-31c-188a-17h-15.5w-4r-188a0-17h-15.5w-T_BLUE_VITRIOL.solution",
    "lastModified": "2024-05-11T08:05:13.425332760Z"
}