{
    "puzzle": "LUBRICATING_SOLVENTS",
    "score": {
        "cost": 315,
        "instructions": 86,
        "overlap": false,
        "trackless": false,
        "cycles": 184,
        "area": 37,
        "height": 7,
        "width": 7.0,
        "boundingHex": 4,
        "rate": 30.0,
        "areaINF": {
            "level": 0,
            "value": 37.0
        },
        "heightINF": "7",
        "widthINF": 7.0,
        "boundingHexINF": "4"
    },
    "displayLink": "https://files.mors.technology/LUBRICATING_SOLVENTS/315g-184c-37a-86i-3d41bbc8.mp4",
    "dataLink": "https://zlbb.faendir.com/l/om/0c12ecbe/w2788066950/315g-86i-184c-37a-7h-7w-4b-30r-37a0-7h-7w-4b",
    "dataPath": "TOURNAMENT_2022/LUBRICATING_SOLVENTS/315g-86i-184c-37a-7h-7w-4b-30r-37a0-7h-7w-4b_LUBRICATING_SOLVENTS.solution",
    "lastModified": "2024-09-20T22:42:20.882827229Z"
}