{
    "puzzle": "MIRROR_POLISH",
    "score": {
        "cost": 90,
        "instructions": 284,
        "overlap": false,
        "trackless": true,
        "cycles": 1702,
        "area": 990,
        "height": 42,
        "width": 39.0,
        "boundingHex": 28,
        "rate": 284.0,
        "areaINF": {
            "level": 2,
            "value": 36.0
        },
        "heightINF": "INF",
        "widthINF": Infinity,
        "boundingHexINF": "INF"
    },
    "displayLink": "https://files.mors.technology/MIRROR_POLISH/90g-1702c-990a-284i-T-7c3f4ef6.mp4",
    "dataLink": "https://zlbb.faendir.com/l/om/60ac2d66/P269/90g-284i-1702c-990a-42h-39w-28b-284r-36a2-INFh-INFw-INFb-T",
    "dataPath": "JOURNAL_CVIII_III/MIRROR_POLISH/90g-284i-1702c-990a-42h-39w-28b-284r-36a2-INFh-INFw-INFb-T_MIRROR_POLISH.solution",
    "lastModified": "2026-04-27T00:54:58.175086754Z"
}