{
    "puzzle": "HEALTH_TONIC",
    "score": {
        "cost": 80,
        "instructions": 9,
        "overlap": false,
        "trackless": true,
        "cycles": 31,
        "area": 30,
        "height": 6,
        "width": 6.0,
        "boundingHex": 5,
        "rate": 5.0,
        "areaINF": {
            "level": 0,
            "value": 30.0
        },
        "heightINF": "6",
        "widthINF": 6.0,
        "boundingHexINF": "5"
    },
    "displayLink": "https://files.mors.technology/HEALTH_TONIC/80g-31c-30a-9i-T-39eb82b6.mp4",
    "dataLink": "https://zlbb.faendir.com/l/om/a8f760e5/P014/80g-9i-31c-30a-6h-6w-5b-5r-30a0-6h-6w-5b-T",
    "dataPath": "CHAPTER_1/HEALTH_TONIC/80g-9i-31c-30a-6h-6w-5b-5r-30a0-6h-6w-5b-T_HEALTH_TONIC.solution"
}