{
    "puzzle": "EXPLORER_S_SALVE",
    "score": {
        "cost": 660,
        "instructions": 375,
        "overlap": false,
        "trackless": false,
        "cycles": 38,
        "area": 226,
        "height": 16,
        "width": 15.0,
        "boundingHex": 13,
        "rate": 6.17,
        "areaINF": {
            "level": 0,
            "value": 226.0
        },
        "heightINF": "16",
        "widthINF": 15.0,
        "boundingHexINF": "13"
    },
    "displayLink": "https://files.mors.technology/EXPLORER_S_SALVE/660g-38c-226a-375i-029f8133.mp4",
    "dataLink": "https://zlbb.faendir.com/l/om/efbc775f/P059/660g-375i-38c-226a-16h-15w-13b-6.17r-226a0-16h-15w-13b",
    "dataPath": "JOURNAL_II/EXPLORER_S_SALVE/660g-375i-38c-226a-16h-15w-13b-6.17r-226a0-16h-15w-13b_EXPLORER_S_SALVE.solution",
    "lastModified": "2025-12-11T15:07:18.448931016Z"
}