{
    "puzzle": "VIRULENT_VECTOR",
    "score": {
        "cost": 245,
        "instructions": 876,
        "overlap": false,
        "trackless": false,
        "cycles": 176,
        "area": 76,
        "height": 10,
        "width": 10.0,
        "boundingHex": 8,
        "rate": 30.0,
        "areaINF": {
            "level": 0,
            "value": 76.0
        },
        "heightINF": "10",
        "widthINF": 10.0,
        "boundingHexINF": "8"
    },
    "displayLink": "https://files.mors.technology/VIRULENT_VECTOR/245g-176c-76a-876i-a86c5734.mp4",
    "dataLink": "https://zlbb.faendir.com/l/om/a9ded947/w1698785238/245g-876i-176c-76a-10h-10w-8b-30r-76a0-10h-10w-8b",
    "dataPath": "TOURNAMENT_2019/VIRULENT_VECTOR/245g-876i-176c-76a-10h-10w-8b-30r-76a0-10h-10w-8b_VIRULENT_VECTOR.solution",
    "lastModified": "2025-03-31T19:55:36.860682456Z"
}