{
    "puzzle": "CONNECT_THE_DOTS",
    "score": {
        "cost": 115,
        "instructions": 24,
        "overlap": false,
        "trackless": false,
        "cycles": 31,
        "area": 18,
        "height": 5,
        "width": 5.0,
        "rate": 5.0,
        "areaINF": {
            "level": 0,
            "value": 18.0
        },
        "heightINF": "5",
        "widthINF": 5.0
    },
    "displayLink": "https://files.mors.technology/CONNECT_THE_DOTS/115g-31c-18a-24i-551a4307.mp4",
    "dataLink": "https://zlbb.faendir.com/l/om/84d73f5f/w3101135731/115g-24i-31c-18a-5h-5w-5r-18a0-5h-5w",
    "dataPath": "TOURNAMENT_2020/CONNECT_THE_DOTS/115g-24i-31c-18a-5h-5w-5r-18a0-5h-5w_CONNECT_THE_DOTS.solution",
    "lastModified": "2024-04-02T15:02:56.531701855Z"
}