{
    "puzzle": "ABLATIVE_CRYSTAL",
    "score": {
        "cost": 75,
        "instructions": 200,
        "overlap": false,
        "trackless": false,
        "cycles": 1197,
        "area": 55,
        "height": 9,
        "width": 7.5,
        "boundingHex": 5,
        "rate": 200.0,
        "areaINF": {
            "level": 0,
            "value": 55.0
        },
        "heightINF": "9",
        "widthINF": 7.5,
        "boundingHexINF": "5"
    },
    "displayLink": "https://files.mors.technology/ABLATIVE_CRYSTAL/75g-1197c-55a-200i-2140f81c.mp4",
    "dataLink": "https://zlbb.faendir.com/l/om/9fc0c8a5/P068/75g-200i-1197c-55a-9h-7.5w-5b-200r-55a0-9h-7.5w-5b",
    "dataPath": "JOURNAL_III/ABLATIVE_CRYSTAL/75g-200i-1197c-55a-9h-7.5w-5b-200r-55a0-9h-7.5w-5b_ABLATIVE_CRYSTAL.solution",
    "lastModified": "2024-05-26T15:03:49.103435574Z"
}