{
    "puzzle": "BLOOD_STANCHING_POWDER",
    "score": {
        "cost": 1350,
        "instructions": 4,
        "overlap": false,
        "trackless": false,
        "cycles": 2647,
        "area": 721,
        "height": 23,
        "width": 28.5,
        "rate": 444.0,
        "areaINF": {
            "level": 0,
            "value": 721.0
        },
        "heightINF": "23",
        "widthINF": 28.5
    },
    "displayLink": "https://cdn.discordapp.com/attachments/760122588143157278/1144628677548720148/Opus_Magnum_-_Blood-Stanching_Powder_1350G_2647_721_2023-08-25-15-42-00.gif",
    "dataLink": "https://zlbb.faendir.com/l/om/d1ae4f8a/P087/1350g-4i-2647c-721a-23h-28.5w-444r-721a0-23h-28.5w",
    "dataPath": "JOURNAL_V/BLOOD_STANCHING_POWDER/1350g-4i-2647c-721a-23h-28.5w-444r-721a0-23h-28.5w_BLOOD_STANCHING_POWDER.solution"
}