{
    "puzzle": "FULMINATION",
    "score": {
        "cost": 140,
        "instructions": 351,
        "overlap": false,
        "trackless": true,
        "cycles": 568,
        "area": 61,
        "height": 10,
        "width": 8.5,
        "boundingHex": 6,
        "rate": 94.5,
        "areaINF": {
            "level": 0,
            "value": 61.0
        },
        "heightINF": "10",
        "widthINF": 8.5,
        "boundingHexINF": "6"
    },
    "displayLink": "https://files.mors.technology/FULMINATION/140g-568c-61a-351i-T-ff446568.mp4",
    "dataLink": "https://zlbb.faendir.com/l/om/a8f760e5/w2788067677/140g-351i-568c-61a-10h-8.5w-6b-94.5r-61a0-10h-8.5w-6b-T",
    "dataPath": "TOURNAMENT_2022/FULMINATION/140g-351i-568c-61a-10h-8.5w-6b-94.5r-61a0-10h-8.5w-6b-T_FULMINATION.solution"
}