{
    "puzzle": "MOORING_CABLE",
    "score": {
        "cost": 235,
        "instructions": 40,
        "overlap": false,
        "trackless": false,
        "cycles": 74,
        "area": 89,
        "height": 9,
        "width": null,
        "boundingHex": null,
        "rate": 9.0,
        "areaINF": {
            "level": 1,
            "value": 6.0
        },
        "heightINF": "9",
        "widthINF": null,
        "boundingHexINF": null
    },
    "displayLink": "https://files.mors.technology/MOORING_CABLE/235g-74c-89a-40i-60f0083d.mp4",
    "dataLink": "https://zlbb.faendir.com/l/om/a7b66b26/P255/235g-40i-74c-89a-9h-9r-6a1-9h",
    "dataPath": "JOURNAL_CVIII_I/MOORING_CABLE/235g-40i-74c-89a-9h-9r-6a1-9h_MOORING_CABLE.solution",
    "lastModified": "2026-04-10T05:21:31.452516713Z"
}