{
    "puzzle": "REACTIVE_CINNABAR",
    "score": {
        "cost": 140,
        "instructions": 11,
        "overlap": false,
        "trackless": true,
        "cycles": 189,
        "area": 103,
        "height": 11,
        "width": 10.5,
        "rate": 18.0,
        "areaINF": {
            "level": 0,
            "value": 103.0
        },
        "heightINF": "11",
        "widthINF": 10.5
    },
    "displayLink": "https://files.mors.technology/REACTIVE_CINNABAR/140g-189c-103a-11i-T-3a49ae77.mp4",
    "dataLink": "https://zlbb.faendir.com/l/om/dd7e3fbd/P056/140g-11i-189c-103a-11h-10.5w-18r-103a0-11h-10.5w-T",
    "dataPath": "JOURNAL_I/REACTIVE_CINNABAR/140g-11i-189c-103a-11h-10.5w-18r-103a0-11h-10.5w-T_REACTIVE_CINNABAR.solution",
    "lastModified": "2024-04-03T07:36:20.368792016Z"
}