{
    "puzzle": "HYPER_VOLATILE_GAS",
    "score": {
        "cost": 345,
        "instructions": 90,
        "overlap": false,
        "trackless": false,
        "cycles": 128,
        "area": 45,
        "height": 3,
        "width": 9.0,
        "rate": 19.0,
        "areaINF": {
            "level": 0,
            "value": 45.0
        },
        "heightINF": "3",
        "widthINF": 9.0
    },
    "displayLink": "https://files.mors.technology/HYPER_VOLATILE_GAS/345g-128c-45a-90i-03026e18.mp4",
    "dataLink": "https://zlbb.faendir.com/l/om/ab955f17/P106/345g-90i-128c-45a-3h-9w-19r-45a0-3h-9w",
    "dataPath": "JOURNAL_IX/HYPER_VOLATILE_GAS/345g-90i-128c-45a-3h-9w-19r-45a0-3h-9w_HYPER_VOLATILE_GAS.solution",
    "lastModified": "2024-03-14T08:35:58.014327478Z"
}