{
    "puzzle": "DO_YOU_REMEMBER",
    "score": {
        "cost": 160,
        "cycles": 878,
        "area": 29,
        "instructions": 259,
        "height": 6,
        "width": 5.5,
        "rate": 146.0,
        "trackless": true
    },
    "displayLink": "https://files.mors.technology/Do-You-Remember-160g-878c-29a-259i-6h-5.5w-146r-T-e8d8d9.gif",
    "dataLink": "https://zlbb.faendir.com/l/om/7469df5/w1698787731/160g-878c-29a-259i-6h-5.5w-146r-T",
    "dataPath": "TOURNAMENT_2019/DO_YOU_REMEMBER/160g-878c-29a-259i-6h-5.5w-146r-T_DO_YOU_REMEMBER.solution",
    "lastModified": "2022-09-10T19:57:36.847315091Z"
}