{
    "puzzle": "DO_YOU_REMEMBER",
    "score": {
        "cost": 825,
        "cycles": 96,
        "area": 90,
        "instructions": 982,
        "height": 3,
        "width": 16.5
    },
    "displayLink": "https://files.mors.technology/Do-You-Remember-825g-96c-90a-982i-3h-16.5w-121ff5.gif",
    "dataLink": "https://zlbb.faendir.com/l/om/e2dbad2/w1698787731/825g-96c-90a-982i-3h-16.5w",
    "dataPath": "TOURNAMENT_2019/DO_YOU_REMEMBER/825g-96c-90a-982i-3h-16.5w_DO_YOU_REMEMBER.solution",
    "lastModified": "2022-11-14T06:34:38.700596804Z"
}