{
    "puzzle": "BUOYANT_CABLE",
    "score": {
        "cost": 200,
        "instructions": 70,
        "overlap": false,
        "trackless": false,
        "cycles": 106,
        "area": 96,
        "height": 3,
        "width": 17.5,
        "rate": 16.0,
        "areaINF": {
            "level": 1,
            "value": 12.0
        },
        "heightINF": "3",
        "widthINF": null
    },
    "displayLink": "https://cdn.discordapp.com/attachments/955013796211085344/1109697451432099960/Opus_Magnum_-_Buoyant_Cable_200G_106_96_2023-05-20-21-20-56.gif",
    "dataLink": "https://zlbb.faendir.com/l/om/bd462078/P062/200g-70i-106c-96a-3h-17.5w-16r-12a1-3h",
    "dataPath": "JOURNAL_II/BUOYANT_CABLE/200g-70i-106c-96a-3h-17.5w-16r-12a1-3h_BUOYANT_CABLE.solution"
}