{
    "puzzle": "HANGOVER_CURE",
    "score": {
        "cost": 100,
        "instructions": 15,
        "overlap": false,
        "trackless": true,
        "cycles": 62,
        "area": 40,
        "height": 7,
        "width": 6.0,
        "boundingHex": 5,
        "rate": 6.0,
        "areaINF": {
            "level": 0,
            "value": 40.0
        },
        "heightINF": "7",
        "widthINF": 6.0,
        "boundingHexINF": "5"
    },
    "displayLink": "https://files.mors.technology/HANGOVER_CURE/100g-62c-40a-15i-T-71727eba.mp4",
    "dataLink": "https://zlbb.faendir.com/l/om/8b29ddac/P013/100g-15i-62c-40a-7h-6w-5b-6r-40a0-7h-6w-5b-T",
    "dataPath": "CHAPTER_1/HANGOVER_CURE/100g-15i-62c-40a-7h-6w-5b-6r-40a0-7h-6w-5b-T_HANGOVER_CURE.solution",
    "lastModified": "2025-07-07T00:38:33.262506905Z"
}