{
    "puzzle": "SWAMP_FIBER",
    "score": {
        "cost": 80,
        "instructions": 1078,
        "overlap": false,
        "trackless": false,
        "cycles": 1078,
        "area": 95,
        "height": 6,
        "width": null,
        "boundingHex": null,
        "rate": null,
        "areaINF": null,
        "heightINF": null,
        "widthINF": null,
        "boundingHexINF": null
    },
    "displayLink": "https://files.mors.technology/SWAMP_FIBER/80g-1078c-95a-1078i-26c8ad44.mp4",
    "dataLink": "https://zlbb.faendir.com/l/om/6e290c88/w2501727889/80g-1078i-1078c-95a-6h",
    "dataPath": "TOURNAMENT_2020/SWAMP_FIBER/80g-1078i-1078c-95a-6h_SWAMP_FIBER.solution",
    "lastModified": "2025-01-20T07:25:21.892207154Z"
}