{
    "puzzle": "ARMOR_FILAMENT",
    "score": {
        "cost": 160,
        "cycles": 60,
        "area": 162,
        "instructions": 12,
        "height": 18,
        "width": 15.5,
        "rate": 8.0,
        "trackless": true
    },
    "displayLink": "https://cdn.discordapp.com/attachments/909638277756243978/921242272287322132/Opus_Magnum_-_Armor_Filament_160G_60_162_2021-12-16-19-27-23.gif",
    "dataLink": "https://git.io/JDrwC",
    "dataPath": "CHAPTER_2/ARMOR_FILAMENT/160g-60c-162a-12i-18h-15.5w-8r-T_ARMOR_FILAMENT.solution"
}