{
    "puzzle": "ARMOR_FILAMENT",
    "score": {
        "cost": 70,
        "instructions": 62,
        "overlap": false,
        "trackless": true,
        "cycles": 243,
        "area": 20,
        "height": 3,
        "width": 9.0,
        "rate": 41.34,
        "areaINF": null,
        "heightINF": "3",
        "widthINF": null
    },
    "displayLink": "https://files.mors.technology/Armor-Filament-70g-243c-20a-62i-3h-9w-41.34r-T-d8dbdd.gif",
    "dataLink": "https://zlbb.faendir.com/l/om/db09463/P020/70g-62i-243c-20a-3h-9w-41.34r-3h-T",
    "dataPath": "CHAPTER_2/ARMOR_FILAMENT/70g-62i-243c-20a-3h-9w-41.34r-3h-T_ARMOR_FILAMENT.solution"
}