{
    "puzzle": "ARMOR_FILAMENT",
    "score": {
        "cost": 90,
        "instructions": 8,
        "overlap": true,
        "trackless": true,
        "cycles": 60,
        "area": 125,
        "height": 14,
        "width": null,
        "boundingHex": null,
        "rate": null,
        "areaINF": null,
        "heightINF": null,
        "widthINF": null,
        "boundingHexINF": null
    },
    "displayLink": "https://files.mors.technology/ARMOR_FILAMENT/90g-60c-125a-8i-O-T-d9388c41.mp4",
    "dataLink": "https://zlbb.faendir.com/l/om/a8f760e5/P020/90g-8i-60c-125a-14h-O-T",
    "dataPath": "CHAPTER_2/ARMOR_FILAMENT/90g-8i-60c-125a-14h-O-T_ARMOR_FILAMENT.solution"
}