{
    "puzzle": "UNWINDING",
    "score": {
        "cost": 65,
        "instructions": 15,
        "overlap": false,
        "trackless": false,
        "cycles": 88,
        "area": 48,
        "height": 8,
        "width": 7.5,
        "rate": 15.0,
        "areaINF": {
            "level": 0,
            "value": 48.0
        },
        "heightINF": "8",
        "widthINF": 7.5
    },
    "displayLink": "https://cdn.discordapp.com/attachments/1076968243295698984/1214825426678190140/Opus_Magnum_-_UNWINDING_65G_88_48_2024-03-06-01-42-02.gif?ex=65fa8558&is=65e81058&hm=e65a868e1953607bd02025e1fc99a5bf650151bf738583e274b5196c31d15241&",
    "dataLink": "https://zlbb.faendir.com/l/om/e4c40328/w1611998067/65g-15i-88c-48a-8h-7.5w-15r-48a0-8h-7.5w",
    "dataPath": "TOURNAMENT_2019/UNWINDING/65g-15i-88c-48a-8h-7.5w-15r-48a0-8h-7.5w_UNWINDING.solution",
    "lastModified": "2024-03-06T06:42:00.359200059Z"
}