{
    "puzzle": "ELECTRUM_SEPARATION",
    "score": {
        "cost": 1235,
        "instructions": 577,
        "overlap": false,
        "trackless": false,
        "cycles": 32,
        "area": 522,
        "height": 26,
        "width": null,
        "boundingHex": null,
        "rate": null,
        "areaINF": null,
        "heightINF": null,
        "widthINF": null,
        "boundingHexINF": null
    },
    "displayLink": "https://files.mors.technology/ELECTRUM_SEPARATION/1235g-32c-522a-577i-0d026a85.mp4",
    "dataLink": "https://zlbb.faendir.com/l/om/a8f760e5/P103/1235g-577i-32c-522a-26h",
    "dataPath": "JOURNAL_VIII/ELECTRUM_SEPARATION/1235g-577i-32c-522a-26h_ELECTRUM_SEPARATION.solution"
}