{
    "puzzle": "ELECTRUM_SEPARATION",
    "score": {
        "cost": 205,
        "instructions": 56,
        "overlap": false,
        "trackless": false,
        "cycles": 176,
        "area": 132,
        "height": 13,
        "width": null,
        "boundingHex": null,
        "rate": 8.0,
        "areaINF": {
            "level": 1,
            "value": 2.0
        },
        "heightINF": "13",
        "widthINF": null,
        "boundingHexINF": null
    },
    "displayLink": "https://files.mors.technology/ELECTRUM_SEPARATION/205g-176c-132a-56i-6b50df65.mp4",
    "dataLink": "https://zlbb.faendir.com/l/om/e4cdcd05/P103/205g-56i-176c-132a-13h-8r-2a1-13h",
    "dataPath": "JOURNAL_VIII/ELECTRUM_SEPARATION/205g-56i-176c-132a-13h-8r-2a1-13h_ELECTRUM_SEPARATION.solution",
    "lastModified": "2026-06-17T09:14:39.728116525Z"
}