{
    "puzzle": "PROSPECTOR_S_SOLVENT",
    "score": {
        "cost": 200,
        "instructions": 63,
        "overlap": false,
        "trackless": true,
        "cycles": 107,
        "area": 63,
        "height": 9,
        "width": 9.5,
        "boundingHex": 6,
        "rate": 16.0,
        "areaINF": {
            "level": 0,
            "value": 63.0
        },
        "heightINF": "9",
        "widthINF": 9.5,
        "boundingHexINF": "6"
    },
    "displayLink": "https://files.mors.technology/PROSPECTOR_S_SOLVENT/200g-107c-63a-63i-T-bfd22cf5.mp4",
    "dataLink": "https://zlbb.faendir.com/l/om/e8496221/P261/200g-63i-107c-63a-9h-9.5w-6b-16r-63a0-9h-9.5w-6b-T",
    "dataPath": "JOURNAL_CVIII_II/PROSPECTOR_S_SOLVENT/200g-63i-107c-63a-9h-9.5w-6b-16r-63a0-9h-9.5w-6b-T_PROSPECTOR_S_SOLVENT.solution",
    "lastModified": "2026-04-07T22:29:51.399014792Z"
}