{
    "puzzle": "LUSTRE",
    "score": {
        "cost": 210,
        "instructions": 194,
        "overlap": false,
        "trackless": true,
        "cycles": 578,
        "area": 73,
        "height": null,
        "width": null,
        "boundingHex": null,
        "rate": 93.0,
        "areaINF": {
            "level": 0,
            "value": 73.0
        },
        "heightINF": null,
        "widthINF": null,
        "boundingHexINF": null
    },
    "displayLink": "https://files.mors.technology/LUSTRE/210g-578c-73a-194i-T-04ef700f.mp4",
    "dataLink": "https://zlbb.faendir.com/l/om/99704016/P090/210g-194i-578c-73a-93r-73a0-T",
    "dataPath": "JOURNAL_VI/LUSTRE/210g-194i-578c-73a-93r-73a0-T_LUSTRE.solution",
    "lastModified": "2026-02-14T06:07:21.517118395Z"
}