{
    "puzzle": "POTENT_POTABLES",
    "score": {
        "cost": 110,
        "instructions": 46,
        "overlap": false,
        "trackless": false,
        "cycles": 112,
        "area": 55,
        "height": 7,
        "width": 7.5,
        "boundingHex": 7,
        "rate": 18.0,
        "areaINF": {
            "level": 0,
            "value": 55.0
        },
        "heightINF": "7",
        "widthINF": 7.5,
        "boundingHexINF": "7"
    },
    "displayLink": "https://files.mors.technology/POTENT_POTABLES/110g-112c-55a-46i-33883cd4.mp4",
    "dataLink": "https://zlbb.faendir.com/l/om/38275238/w2501727721/110g-46i-112c-55a-7h-7.5w-7b-18r-55a0-7h-7.5w-7b",
    "dataPath": "TOURNAMENT_2020/POTENT_POTABLES/110g-46i-112c-55a-7h-7.5w-7b-18r-55a0-7h-7.5w-7b_POTENT_POTABLES.solution",
    "lastModified": "2024-08-19T18:53:38.390057623Z"
}