{
    "puzzle": "PRECISION_MACHINE_OIL",
    "score": {
        "cost": 75,
        "cycles": 247,
        "area": 15,
        "instructions": 42,
        "height": 2,
        "width": 4.5,
        "rate": 42.0
    },
    "displayLink": "https://files.mors.technology/Precision-Machine-Oil-75g-247c-15a-42i-2h-4.5w-42r-9ea13b.gif",
    "dataLink": "https://zlbb.faendir.com/l/om/673f436/P012/75g-247c-15a-42i-2h-4.5w-42r",
    "dataPath": "CHAPTER_1/PRECISION_MACHINE_OIL/75g-247c-15a-42i-2h-4.5w-42r_PRECISION_MACHINE_OIL.solution",
    "lastModified": "2022-10-27T01:06:12.675315579Z"
}