{
    "puzzle": "ANIMISMUS_BUFFER",
    "score": {
        "cost": 245,
        "instructions": 70,
        "overlap": false,
        "trackless": false,
        "cycles": 151,
        "area": 77,
        "height": 13,
        "width": 7.5,
        "rate": 24.0,
        "areaINF": {
            "level": 1,
            "value": 3.0
        },
        "heightINF": "INF",
        "widthINF": 7.5
    },
    "displayLink": "https://imgur.com/T4ea46o.gif",
    "dataLink": "https://zlbb.faendir.com/l/om/89b06f8f/P104/245g-70i-151c-77a-13h-7.5w-24r-3a1-INFh-7.5w",
    "dataPath": "JOURNAL_VIII/ANIMISMUS_BUFFER/245g-70i-151c-77a-13h-7.5w-24r-3a1-INFh-7.5w_ANIMISMUS_BUFFER.solution",
    "lastModified": "2024-03-20T05:06:20.470743787Z"
}