{
    "puzzle": "BIOSTEEL_FILAMENT",
    "score": {
        "cost": 220,
        "instructions": 70,
        "overlap": false,
        "trackless": false,
        "cycles": 94,
        "area": 103,
        "height": 7,
        "width": null,
        "boundingHex": null,
        "rate": null,
        "areaINF": null,
        "heightINF": null,
        "widthINF": null,
        "boundingHexINF": null
    },
    "displayLink": "https://files.mors.technology/BIOSTEEL_FILAMENT/220g-94c-103a-70i-0ea4f81c.mp4",
    "dataLink": "https://zlbb.faendir.com/l/om/a8f760e5/w2946684529/220g-70i-94c-103a-7h",
    "dataPath": "TOURNAMENT_2023/BIOSTEEL_FILAMENT/220g-70i-94c-103a-7h_BIOSTEEL_FILAMENT.solution"
}