{
    "puzzle": "BIOSTEEL_FILAMENT",
    "score": {
        "cost": 975,
        "instructions": 369,
        "overlap": false,
        "trackless": false,
        "cycles": 37,
        "area": 196,
        "height": 13,
        "width": null,
        "boundingHex": null,
        "rate": null,
        "areaINF": null,
        "heightINF": null,
        "widthINF": null,
        "boundingHexINF": null
    },
    "displayLink": "https://files.mors.technology/BIOSTEEL_FILAMENT/975g-37c-196a-369i-4533c491.mp4",
    "dataLink": "https://zlbb.faendir.com/l/om/b2a5807b/w2946684529/975g-369i-37c-196a-13h",
    "dataPath": "TOURNAMENT_2023/BIOSTEEL_FILAMENT/975g-369i-37c-196a-13h_BIOSTEEL_FILAMENT.solution"
}