{
    "puzzle": "ASSASSIN_S_FILAMENT",
    "score": {
        "cost": 365,
        "instructions": 230,
        "overlap": true,
        "trackless": false,
        "cycles": 37,
        "area": 318,
        "height": 23,
        "width": 19.5,
        "rate": null,
        "areaINF": null,
        "heightINF": null,
        "widthINF": null
    },
    "displayLink": "https://files.mors.technology/ASSASSIN_S_FILAMENT/365g-37c-318a-230i-O-80351fb6.mp4",
    "dataLink": "https://zlbb.faendir.com/l/om/9e66a565/P097/365g-230i-37c-318a-23h-19.5w-O",
    "dataPath": "JOURNAL_VII/ASSASSIN_S_FILAMENT/365g-230i-37c-318a-23h-19.5w-O_ASSASSIN_S_FILAMENT.solution",
    "lastModified": "2024-02-13T09:14:35.048043190Z"
}