{
    "puzzle": "LAMBENT_II_IX",
    "score": {
        "cost": 50,
        "cycles": 968,
        "area": 50,
        "instructions": 162,
        "height": 9,
        "width": 7.5,
        "rate": 162.0
    },
    "displayLink": "https://files.mors.technology/Lambent-II-IX-50g-968c-50a-162i-9h-7.5w-162r-f70437.mp4",
    "dataLink": "https://zlbb.faendir.com/l/om/a77bf20c0/P058/50g-968c-50a-162i-9h-7.5w-162r_LAMBENT_II_IX",
    "dataPath": "JOURNAL_I/LAMBENT_II_IX/50g-968c-50a-162i-9h-7.5w-162r_LAMBENT_II_IX.solution",
    "lastModified": "2022-08-14T14:04:07Z"
}

