{
    "puzzle": "LAMBENT_II_IX",
    "score": {
        "cost": 575,
        "instructions": 115,
        "overlap": false,
        "trackless": false,
        "cycles": 98,
        "area": 50,
        "height": 8,
        "width": 7.5,
        "boundingHex": 6,
        "rate": 16.0,
        "areaINF": {
            "level": 0,
            "value": 50.0
        },
        "heightINF": "8",
        "widthINF": 7.5,
        "boundingHexINF": "6"
    },
    "displayLink": "https://files.mors.technology/Lambent-II-IX-575g-98c-50a-115i-8h-7.5w-16r-569367.gif",
    "dataLink": "https://zlbb.faendir.com/l/om/b2a5807b/P058/575g-115i-98c-50a-8h-7.5w-6b-16r-50a0-8h-7.5w-6b",
    "dataPath": "JOURNAL_I/LAMBENT_II_IX/575g-115i-98c-50a-8h-7.5w-6b-16r-50a0-8h-7.5w-6b_LAMBENT_II_IX.solution"
}