{
    "puzzle": "VAPOROUS_SOLVENT",
    "score": {
        "cost": 1195,
        "instructions": 328,
        "overlap": true,
        "trackless": false,
        "cycles": 104,
        "area": 596,
        "height": 31,
        "width": 23.5,
        "rate": 5.0,
        "areaINF": "596",
        "heightINF": "31",
        "widthINF": 23.5
    },
    "displayLink": "https://cdn.discordapp.com/attachments/760122588143157278/1151842701860425728/Opus_Magnum_-_Vaporous_Solvent_1195G_104_596_2023-09-14-13-33-17.gif",
    "dataLink": "https://zlbb.faendir.com/l/om/a2aaba9/P098/1195g-328i-104c-596a-31h-23.5w-5r-596a-31h-23.5w-O",
    "dataPath": "JOURNAL_VII/VAPOROUS_SOLVENT/1195g-328i-104c-596a-31h-23.5w-5r-596a-31h-23.5w-O_VAPOROUS_SOLVENT.solution",
    "lastModified": "2023-09-14T11:31:06.422340994Z"
}