{
    "puzzle": "GALENA_SEPARATION",
    "score": {
        "cost": 300,
        "instructions": 106,
        "overlap": false,
        "trackless": false,
        "cycles": 189,
        "area": 34,
        "height": 3,
        "width": 7.5,
        "boundingHex": 8,
        "rate": 11.67,
        "areaINF": {
            "level": 0,
            "value": 34.0
        },
        "heightINF": "3",
        "widthINF": 7.5,
        "boundingHexINF": "8"
    },
    "displayLink": "https://files.mors.technology/GALENA_SEPARATION/300g-189c-34a-106i-20a41da2.mp4",
    "dataLink": "https://zlbb.faendir.com/l/om/57dcac00/P207/300g-106i-189c-34a-3h-7.5w-8b-11.67r-34a0-3h-7.5w-8b",
    "dataPath": "DRM_CHAPTER_1/GALENA_SEPARATION/300g-106i-189c-34a-3h-7.5w-8b-11.67r-34a0-3h-7.5w-8b_GALENA_SEPARATION.solution",
    "lastModified": "2026-04-04T21:15:12.478442381Z"
}