{
    "puzzle": "FILM_CRYSTAL",
    "score": {
        "cost": 65,
        "instructions": 77,
        "overlap": false,
        "trackless": false,
        "cycles": 1384,
        "area": 87,
        "height": 11,
        "width": 10.5,
        "rate": 231.0,
        "areaINF": "87",
        "heightINF": "11",
        "widthINF": 10.5
    },
    "displayLink": "https://i.postimg.cc/0y77Gjvs/814-OM22-Film-Crystal-B-GI77-1-3-T-65-G-1384-C-87-A-77-I-7-P.gif",
    "dataLink": "https://zlbb.faendir.com/l/om/c4f0fbd/w2788067038/65g-77i-1384c-87a-11h-10.5w-231r-87a-11h-10.5w",
    "dataPath": "TOURNAMENT_2022/FILM_CRYSTAL/65g-77i-1384c-87a-11h-10.5w-231r-87a-11h-10.5w_FILM_CRYSTAL.solution",
    "lastModified": "2023-06-19T07:21:08.764139329Z"
}