{
    "puzzle": "WASTE_RECLAMATION",
    "score": {
        "cost": 120,
        "instructions": 814,
        "overlap": false,
        "trackless": false,
        "cycles": 769,
        "area": 38,
        "height": 9,
        "width": 3.5,
        "rate": null,
        "areaINF": null,
        "heightINF": null,
        "widthINF": null
    },
    "displayLink": "https://files.mors.technology/WASTE_RECLAMATION/120g-769c-38a-814i-ab425bb6.mp4",
    "dataLink": "https://zlbb.faendir.com/l/om/923feca9/w2946683186/120g-814i-769c-38a-9h-3.5w",
    "dataPath": "TOURNAMENT_2023/WASTE_RECLAMATION/120g-814i-769c-38a-9h-3.5w_WASTE_RECLAMATION.solution",
    "lastModified": "2024-02-23T04:38:28.108673526Z"
}