{
    "puzzle": "PURIFIED_GOLD",
    "score": {
        "cost": 230,
        "cycles": 151,
        "area": 17,
        "instructions": 3,
        "height": 4,
        "width": 4.5,
        "rate": 24.0,
        "trackless": true,
        "overlap": true
    },
    "displayLink": "https://files.mors.technology/Purified-Gold-230g-151c-17a-3i-4h-4.5w-24r-T-O-5256ea.gif",
    "dataLink": "https://zlbb.faendir.com/l/om/3f0b124/P036/230g-151c-17a-3i-4h-4.5w-24r-O-T",
    "dataPath": "CHAPTER_4/PURIFIED_GOLD/230g-151c-17a-3i-4h-4.5w-24r-O-T_PURIFIED_GOLD.solution",
    "lastModified": "2022-09-12T20:51:26.098236601Z"
}