{
    "puzzle": "RUST_REMOVAL",
    "score": {
        "cost": 350,
        "instructions": 18,
        "overlap": true,
        "trackless": false,
        "cycles": 6,
        "area": 35,
        "height": 4,
        "width": 9.0,
        "rate": null,
        "areaINF": null,
        "heightINF": null,
        "widthINF": null
    },
    "displayLink": "https://files.mors.technology/Rust-Removal-350g-6c-35a-18i-4h-9w-O-541a4e.gif",
    "dataLink": "https://zlbb.faendir.com/l/om/5c5a7805b/w2788066771/350g-18i-6c-35a-4h-9w-O",
    "dataPath": "TOURNAMENT_2022/RUST_REMOVAL/350g-18i-6c-35a-4h-9w-O_RUST_REMOVAL.solution"
}