{
    "puzzle": "QUINTESSENTIAL_MEDIUM",
    "score": {
        "cost": 140,
        "cycles": 286,
        "area": 98,
        "instructions": 47,
        "height": 7,
        "width": 32.5,
        "rate": 48.0
    },
    "displayLink": "https://cdn.discordapp.com/attachments/909638277756243978/960280987676319754/g2.gif",
    "dataLink": "https://zlbb.faendir.com/l/om/a77bf20c0/P107/140g-286c-98a-47i-7h-32.5w-48r_QUINTESSENTIAL_MEDIUM",
    "dataPath": "JOURNAL_IX/QUINTESSENTIAL_MEDIUM/140g-286c-98a-47i-7h-32.5w-48r_QUINTESSENTIAL_MEDIUM.solution",
    "lastModified": "2022-08-14T14:04:07Z"
}