{
    "puzzle": "QUINTESSENTIAL_MEDIUM",
    "score": {
        "cost": 4490,
        "instructions": 2115,
        "overlap": false,
        "trackless": false,
        "cycles": 551,
        "area": 864,
        "height": 3,
        "width": 150.5,
        "boundingHex": 151,
        "rate": 6.0,
        "areaINF": {
            "level": 0,
            "value": 864.0
        },
        "heightINF": "3",
        "widthINF": 150.5,
        "boundingHexINF": "151"
    },
    "displayLink": "https://files.mors.technology/QUINTESSENTIAL_MEDIUM/4490g-551c-864a-2115i-38847eef.mp4",
    "dataLink": "https://zlbb.faendir.com/l/om/7ba691e0/P107/4490g-2115i-551c-864a-3h-150.5w-151b-6r-864a0-3h-150.5w-151b",
    "dataPath": "JOURNAL_IX/QUINTESSENTIAL_MEDIUM/4490g-2115i-551c-864a-3h-150.5w-151b-6r-864a0-3h-150.5w-151b_QUINTESSENTIAL_MEDIUM.solution",
    "lastModified": "2025-05-28T00:01:11.489269959Z"
}