{
    "puzzle": "ALCOHOL_SEPARATION",
    "score": {
        "cost": 175,
        "instructions": 3,
        "overlap": false,
        "trackless": false,
        "cycles": 186,
        "area": 70,
        "height": 9,
        "width": 9.5,
        "boundingHex": 7,
        "rate": 27.0,
        "areaINF": {
            "level": 0,
            "value": 70.0
        },
        "heightINF": "9",
        "widthINF": 9.5,
        "boundingHexINF": "7"
    },
    "displayLink": "https://files.mors.technology/ALCOHOL_SEPARATION/175g-186c-70a-3i-6e342746.mp4",
    "dataLink": "https://zlbb.faendir.com/l/om/b2a5807b/P024/175g-3i-186c-70a-9h-9.5w-7b-27r-70a0-9h-9.5w-7b",
    "dataPath": "CHAPTER_3/ALCOHOL_SEPARATION/175g-3i-186c-70a-9h-9.5w-7b-27r-70a0-9h-9.5w-7b_ALCOHOL_SEPARATION.solution"
}