{
    "puzzle": "ALCOHOL_SEPARATION",
    "score": {
        "cost": 405,
        "instructions": 204,
        "overlap": false,
        "trackless": false,
        "cycles": 57,
        "area": 57,
        "height": 3,
        "width": 11.5,
        "boundingHex": 11,
        "rate": 3.0,
        "areaINF": {
            "level": 0,
            "value": 57.0
        },
        "heightINF": "3",
        "widthINF": 11.5,
        "boundingHexINF": "11"
    },
    "displayLink": "https://files.mors.technology/ALCOHOL_SEPARATION/405g-57c-57a-204i-3fe2e7e5.mp4",
    "dataLink": "https://zlbb.faendir.com/l/om/74dc0cd3/P024/405g-204i-57c-57a-3h-11.5w-11b-3r-57a0-3h-11.5w-11b",
    "dataPath": "CHAPTER_3/ALCOHOL_SEPARATION/405g-204i-57c-57a-3h-11.5w-11b-3r-57a0-3h-11.5w-11b_ALCOHOL_SEPARATION.solution",
    "lastModified": "2024-05-30T22:25:51.860529369Z"
}