{
    "puzzle": "LATCH_HOOK_FIREWORKS",
    "score": {
        "cost": 865,
        "instructions": 100,
        "overlap": false,
        "trackless": false,
        "cycles": 67,
        "area": 143,
        "height": 11,
        "width": 14.0,
        "rate": 4.0,
        "areaINF": {
            "level": 0,
            "value": 143.0
        },
        "heightINF": "11",
        "widthINF": 14.0
    },
    "displayLink": "https://i.imgur.com/EteolIZ.gif",
    "dataLink": "https://zlbb.faendir.com/l/om/7a6572db/w3210177679/865g-100i-67c-143a-11h-14w-4r-143a0-11h-14w",
    "dataPath": "TOURNAMENT_2024/LATCH_HOOK_FIREWORKS/865g-100i-67c-143a-11h-14w-4r-143a0-11h-14w_LATCH_HOOK_FIREWORKS.solution",
    "lastModified": "2024-04-08T13:25:18.632169701Z"
}