{
    "puzzle": "WHEEL_REPRESENTATION",
    "score": {
        "cost": 135,
        "instructions": 85,
        "overlap": false,
        "trackless": false,
        "cycles": 437,
        "area": 48,
        "height": 9,
        "width": 5.5,
        "boundingHex": 7,
        "rate": 73.0,
        "areaINF": {
            "level": 0,
            "value": 48.0
        },
        "heightINF": "9",
        "widthINF": 5.5,
        "boundingHexINF": "7"
    },
    "displayLink": "https://files.mors.technology/WHEEL_REPRESENTATION/135g-437c-48a-85i-a042fac5.mp4",
    "dataLink": "https://zlbb.faendir.com/l/om/8c7b14e5/P070/135g-85i-437c-48a-9h-5.5w-7b-73r-48a0-9h-5.5w-7b",
    "dataPath": "JOURNAL_IV/WHEEL_REPRESENTATION/135g-85i-437c-48a-9h-5.5w-7b-73r-48a0-9h-5.5w-7b_WHEEL_REPRESENTATION.solution",
    "lastModified": "2024-07-16T04:14:15.216761446Z"
}