{
    "puzzle": "VISILLARY_ANAESTHETIC",
    "score": {
        "cost": 2650,
        "instructions": 850,
        "overlap": false,
        "trackless": false,
        "cycles": 28,
        "area": 490,
        "height": 27,
        "width": 24.5,
        "boundingHex": 16,
        "rate": 5.0,
        "areaINF": {
            "level": 0,
            "value": 490.0
        },
        "heightINF": "27",
        "widthINF": 24.5,
        "boundingHexINF": "16"
    },
    "displayLink": "https://files.mors.technology/VISILLARY_ANAESTHETIC/2650g-28c-490a-850i-f109a3e5.mp4",
    "dataLink": "https://zlbb.faendir.com/l/om/be388e6c/P102/2650g-850i-28c-490a-27h-24.5w-16b-5r-490a0-27h-24.5w-16b",
    "dataPath": "JOURNAL_VIII/VISILLARY_ANAESTHETIC/2650g-850i-28c-490a-27h-24.5w-16b-5r-490a0-27h-24.5w-16b_VISILLARY_ANAESTHETIC.solution",
    "lastModified": "2024-09-19T15:51:12.737550970Z"
}