{
    "puzzle": "AMELIA_S_CATALYST",
    "score": {
        "cost": 210,
        "instructions": 195,
        "overlap": false,
        "trackless": false,
        "cycles": 518,
        "area": 41,
        "height": 12,
        "width": 2.5,
        "boundingHex": 11,
        "rate": null,
        "areaINF": null,
        "heightINF": null,
        "widthINF": null,
        "boundingHexINF": null
    },
    "displayLink": "https://files.mors.technology/AMELIA_S_CATALYST/210g-518c-41a-195i-de2278ad.mp4",
    "dataLink": "https://zlbb.faendir.com/l/om/727b8081/w3728200264/210g-195i-518c-41a-12h-2.5w-11b",
    "dataPath": "TOURNAMENT_2026/AMELIA_S_CATALYST/210g-195i-518c-41a-12h-2.5w-11b_AMELIA_S_CATALYST.solution",
    "lastModified": "2026-06-27T04:13:02.824678594Z"
}