{
    "puzzle": "TOUCHSTONE",
    "score": {
        "cost": 265,
        "instructions": 313,
        "overlap": false,
        "trackless": false,
        "cycles": 633,
        "area": 56,
        "height": 11,
        "width": 4.0,
        "boundingHex": 11,
        "rate": 106.0,
        "areaINF": {
            "level": 0,
            "value": 56.0
        },
        "heightINF": "11",
        "widthINF": 4.0,
        "boundingHexINF": "11"
    },
    "displayLink": "https://files.mors.technology/TOUCHSTONE/265g-633c-56a-313i-fb308c19.mp4",
    "dataLink": "https://zlbb.faendir.com/l/om/40e2e9a1/w3210172577/265g-313i-633c-56a-11h-4w-11b-106r-56a0-11h-4w-11b",
    "dataPath": "TOURNAMENT_2024/TOUCHSTONE/265g-313i-633c-56a-11h-4w-11b-106r-56a0-11h-4w-11b_TOUCHSTONE.solution",
    "lastModified": "2025-04-13T12:54:06.225021898Z"
}