{
    "puzzle": "PROBE_MODULE",
    "score": {
        "cost": 455,
        "instructions": 49,
        "overlap": false,
        "trackless": false,
        "cycles": 47,
        "area": 95,
        "height": null,
        "width": null,
        "boundingHex": null,
        "rate": 6.0,
        "areaINF": {
            "level": 0,
            "value": 95.0
        },
        "heightINF": null,
        "widthINF": null,
        "boundingHexINF": null
    },
    "displayLink": "https://files.mors.technology/PROBE_MODULE/455g-47c-95a-49i-2c00d7bc.mp4",
    "dataLink": "https://zlbb.faendir.com/l/om/a8f760e5/w2946684660/455g-49i-47c-95a-6r-95a0",
    "dataPath": "TOURNAMENT_2023/PROBE_MODULE/455g-49i-47c-95a-6r-95a0_PROBE_MODULE.solution"
}