{
    "puzzle": "SAILCLOTH_THREAD",
    "score": {
        "cost": 480,
        "instructions": 259,
        "overlap": false,
        "trackless": false,
        "cycles": 28,
        "area": 269,
        "height": 22,
        "width": null,
        "boundingHex": null,
        "rate": null,
        "areaINF": null,
        "heightINF": null,
        "widthINF": null,
        "boundingHexINF": null
    },
    "displayLink": "https://files.mors.technology/SAILCLOTH_THREAD/480g-28c-269a-259i-486b3a23.mp4",
    "dataLink": "https://zlbb.faendir.com/l/om/a8f760e5/P061/480g-259i-28c-269a-22h",
    "dataPath": "JOURNAL_II/SAILCLOTH_THREAD/480g-259i-28c-269a-22h_SAILCLOTH_THREAD.solution"
}