{
    "puzzle": "SAILCLOTH_THREAD",
    "score": {
        "cost": 50,
        "instructions": 144,
        "overlap": false,
        "trackless": false,
        "cycles": 872,
        "area": 71,
        "height": 4,
        "width": 13.0,
        "rate": 144.0,
        "areaINF": {
            "level": 1,
            "value": 9.0
        },
        "heightINF": "4",
        "widthINF": null
    },
    "displayLink": "https://files.mors.technology/SAILCLOTH_THREAD/50g-872c-71a-144i-afa9c41c.mp4",
    "dataLink": "https://zlbb.faendir.com/l/om/295050a2/P061/50g-144i-872c-71a-4h-13w-144r-9a1-4h",
    "dataPath": "JOURNAL_II/SAILCLOTH_THREAD/50g-144i-872c-71a-4h-13w-144r-9a1-4h_SAILCLOTH_THREAD.solution",
    "lastModified": "2024-04-06T17:05:14.244932891Z"
}