{
    "puzzle": "ALCHEMICAL_SLAG",
    "score": {
        "cost": 2595,
        "instructions": 144,
        "overlap": false,
        "trackless": false,
        "cycles": 240,
        "area": 1042,
        "height": 51,
        "width": 45.0,
        "boundingHex": 35,
        "rate": 2.0,
        "areaINF": {
            "level": 0,
            "value": 1042.0
        },
        "heightINF": "51",
        "widthINF": 45.0,
        "boundingHexINF": "35"
    },
    "displayLink": "https://files.mors.technology/ALCHEMICAL_SLAG/2595g-240c-1042a-144i-78032594.mp4",
    "dataLink": "https://zlbb.faendir.com/l/om/9e0e07c8/P099/2595g-144i-240c-1042a-51h-45w-35b-2r-1042a0-51h-45w-35b",
    "dataPath": "JOURNAL_VII/ALCHEMICAL_SLAG/2595g-144i-240c-1042a-51h-45w-35b-2r-1042a0-51h-45w-35b_ALCHEMICAL_SLAG.solution",
    "lastModified": "2024-05-20T07:14:44.594192131Z"
}