{
    "puzzle": "ARTIFICIAL_ORE",
    "score": {
        "cost": 320,
        "instructions": 499,
        "overlap": false,
        "trackless": false,
        "cycles": 140,
        "area": 44,
        "height": null,
        "width": null,
        "boundingHex": null,
        "rate": null,
        "areaINF": null,
        "heightINF": null,
        "widthINF": null,
        "boundingHexINF": null
    },
    "displayLink": "https://files.mors.technology/ARTIFICIAL_ORE/320g-140c-44a-499i-c7598f23.mp4",
    "dataLink": "https://zlbb.faendir.com/l/om/a8f760e5/w2591419339/320g-499i-140c-44a",
    "dataPath": "WEEKLIES_1/ARTIFICIAL_ORE/320g-499i-140c-44a_ARTIFICIAL_ORE.solution"
}