{
    "puzzle": "PANACEA_TO_POISON",
    "score": {
        "cost": 770,
        "instructions": 254,
        "overlap": false,
        "trackless": false,
        "cycles": 36,
        "area": 188,
        "height": 19,
        "width": 16.5,
        "boundingHex": 13,
        "rate": 4.67,
        "areaINF": {
            "level": 1,
            "value": 4.0
        },
        "heightINF": "19",
        "widthINF": Infinity,
        "boundingHexINF": "INF"
    },
    "displayLink": "https://files.mors.technology/PANACEA_TO_POISON/770g-36c-188a-254i-a3e21d64.mp4",
    "dataLink": "https://zlbb.faendir.com/l/om/a8f760e5/w2450511665/770g-254i-36c-188a-19h-16.5w-13b-4.67r-4a1-19h-INFw-INFb",
    "dataPath": "TOURNAMENT_2021/PANACEA_TO_POISON/770g-254i-36c-188a-19h-16.5w-13b-4.67r-4a1-19h-INFw-INFb_PANACEA_TO_POISON.solution"
}