{
    "puzzle": "SWORD_ALLOY",
    "score": {
        "cost": 400,
        "instructions": 376,
        "overlap": false,
        "trackless": false,
        "cycles": 100,
        "area": 109,
        "height": 13,
        "width": null,
        "boundingHex": null,
        "rate": null,
        "areaINF": null,
        "heightINF": null,
        "widthINF": null,
        "boundingHexINF": null
    },
    "displayLink": "https://files.mors.technology/SWORD_ALLOY/400g-100c-109a-376i-8a279468.mp4",
    "dataLink": "https://zlbb.faendir.com/l/om/431473b2/P033/400g-376i-100c-109a-13h",
    "dataPath": "CHAPTER_4/SWORD_ALLOY/400g-376i-100c-109a-13h_SWORD_ALLOY.solution",
    "lastModified": "2026-06-19T00:47:04.127046020Z"
}