{
    "puzzle": "HAIR_PRODUCT",
    "score": {
        "cost": 30,
        "instructions": 29,
        "overlap": false,
        "trackless": true,
        "cycles": 172,
        "area": 12,
        "height": 4,
        "width": 4.0,
        "boundingHex": 3,
        "rate": 29.0,
        "areaINF": {
            "level": 0,
            "value": 12.0
        },
        "heightINF": "4",
        "widthINF": 4.0,
        "boundingHexINF": "3"
    },
    "displayLink": "https://files.mors.technology/HAIR_PRODUCT/30g-172c-12a-29i-T-691ef427.mp4",
    "dataLink": "https://zlbb.faendir.com/l/om/a8f760e5/P016/30g-29i-172c-12a-4h-4w-3b-29r-12a0-4h-4w-3b-T",
    "dataPath": "CHAPTER_2/HAIR_PRODUCT/30g-29i-172c-12a-4h-4w-3b-29r-12a0-4h-4w-3b-T_HAIR_PRODUCT.solution"
}