{
    "puzzle": "ARMOR_POLISH",
    "score": {
        "cost": 1255,
        "instructions": 232,
        "overlap": false,
        "trackless": false,
        "cycles": 100,
        "area": 199,
        "height": 5,
        "width": 24.0,
        "boundingHex": 23,
        "rate": 8.0,
        "areaINF": {
            "level": 0,
            "value": 199.0
        },
        "heightINF": "5",
        "widthINF": 24.0,
        "boundingHexINF": "23"
    },
    "displayLink": "https://files.mors.technology/ARMOR_POLISH/1255g-100c-199a-232i-8478bb16.mp4",
    "dataLink": "https://zlbb.faendir.com/l/om/981a8fc5/P213/1255g-232i-100c-199a-5h-24w-23b-8r-199a0-5h-24w-23b",
    "dataPath": "DRM_CHAPTER_2/ARMOR_POLISH/1255g-232i-100c-199a-5h-24w-23b-8r-199a0-5h-24w-23b_ARMOR_POLISH.solution",
    "lastModified": "2026-06-01T05:17:45.137530830Z"
}