{
    "puzzle": "HIGH_GLOSS_FINISH",
    "score": {
        "cost": 2360,
        "instructions": 308,
        "overlap": false,
        "trackless": true,
        "cycles": 61,
        "area": 669,
        "height": 33,
        "width": 29.5,
        "boundingHex": 24,
        "rate": 4.0,
        "areaINF": {
            "level": 0,
            "value": 669.0
        },
        "heightINF": "33",
        "widthINF": 29.5,
        "boundingHexINF": "24"
    },
    "displayLink": "https://files.mors.technology/HIGH_GLOSS_FINISH/2360g-61c-669a-308i-T-71acf956.mp4",
    "dataLink": "https://zlbb.faendir.com/l/om/520270e4/w2501728349/2360g-308i-61c-669a-33h-29.5w-24b-4r-669a0-33h-29.5w-24b-T",
    "dataPath": "TOURNAMENT_2020/HIGH_GLOSS_FINISH/2360g-308i-61c-669a-33h-29.5w-24b-4r-669a0-33h-29.5w-24b-T_HIGH_GLOSS_FINISH.solution",
    "lastModified": "2025-09-05T13:06:04.862107501Z"
}