{
    "puzzle": "PANACEA",
    "score": {
        "cost": 130,
        "cycles": 556,
        "area": 25,
        "instructions": 1030,
        "height": 6,
        "width": 5.5,
        "rate": 93.16666666666667,
        "trackless": true
    },
    "displayLink": "https://od.lk/s/MV8xNzkxMzA3Mjdf/919_panacea_weekEX_B_GX_S.G.S_6T_130G_556C_25A_1030I_13P.mp4",
    "dataLink": "https://git.io/JMUBN",
    "dataPath": "TOURNAMENT_2019/PANACEA/130g-556c-25a-1030i-6h-5.5w-93.167r-T_PANACEA.solution"
}