{
    "puzzle": "REACTIVE_GOLD",
    "score": {
        "cost": 425,
        "instructions": 63,
        "overlap": true,
        "trackless": false,
        "cycles": 26,
        "area": 25,
        "height": 5,
        "width": 4.5,
        "boundingHex": 6,
        "rate": null,
        "areaINF": null,
        "heightINF": null,
        "widthINF": null,
        "boundingHexINF": null
    },
    "displayLink": "https://files.mors.technology/Reactive-Gold-425g-26c-25a-63i-5h-4.5w-O-83f2bf.gif",
    "dataLink": "https://zlbb.faendir.com/l/om/b2a5807b/P095/425g-63i-26c-25a-5h-4.5w-6b-O",
    "dataPath": "JOURNAL_VII/REACTIVE_GOLD/425g-63i-26c-25a-5h-4.5w-6b-O_REACTIVE_GOLD.solution"
}