{
    "puzzle": "REACTIVE_GOLD",
    "score": {
        "cost": 580,
        "instructions": 36,
        "overlap": false,
        "trackless": false,
        "cycles": 99,
        "area": 126,
        "height": 15,
        "width": 12.5,
        "rate": 8.0,
        "areaINF": "126",
        "heightINF": "15",
        "widthINF": 12.5
    },
    "displayLink": "https://i.imgur.com/jRNyu4O.gif",
    "dataLink": "https://zlbb.faendir.com/l/om/9f17f86/P095/580g-36i-99c-126a-15h-12.5w-8r-126a-15h-12.5w",
    "dataPath": "JOURNAL_VII/REACTIVE_GOLD/580g-36i-99c-126a-15h-12.5w-8r-126a-15h-12.5w_REACTIVE_GOLD.solution",
    "lastModified": "2023-10-15T02:25:57.354231397Z"
}